firstlinear/__init__.py
firstlinear/pypi.py
predmaintenance2020ai4i-0.1.dist-info/METADATA
predmaintenance2020ai4i-0.1.dist-info/WHEEL
predmaintenance2020ai4i-0.1.dist-info/licence.txt
predmaintenance2020ai4i-0.1.dist-info/top_level.txt
predmaintenance2020ai4i-0.1.dist-info/RECORD
