Metadata-Version: 2.1
Name: predmaintenance2020ai4i
Version: 0.1
Summary: basic functions to use for building linear model for uci predictive maintenance ai4i2020 dataset
Home-page: UNKNOWN
Author: Vijeyeta Sharma
Author-email: UNKNOWN
License: UNKNOWN
Platform: UNKNOWN
